certReport/__init__.py
certReport/main.py
certReport/databaseFunctions/__init__.py
certReport/databaseFunctions/databaseManager.py
certreport-3.3.3.1.dist-info/METADATA
certreport-3.3.3.1.dist-info/WHEEL
certreport-3.3.3.1.dist-info/entry_points.txt
certreport-3.3.3.1.dist-info/top_level.txt
certreport-3.3.3.1.dist-info/RECORD
