Metadata-Version: 2.4
Name: certReport
Version: 3.3.3.1
Summary: This script supports the reporting of Authenticode Certificates by reducing the effort on individuals to report.
Author-email: Squiblydoo <Squiblydoo@pm.me>
Project-URL: Homepage, https://github.com/Squiblydoo/certReport
Project-URL: Bug Tracker, https://github.com/Squiblydoo/certReport/issues
Classifier: Programming Language :: Python :: 3
Classifier: License :: OSI Approved :: BSD License
Classifier: Operating System :: OS Independent
Requires-Python: >=3.8
Requires-Dist: requests>=2.31.0
Provides-Extra: dev
Requires-Dist: pytest>=6.2.4; extra == "dev"
